picard_tool/__init__.py
picard_tool/__main__.py
picard_tool/main.py
picard_tool/tools/__init__.py
picard_tool/tools/bam_stats.py
picard_tool/tools/picard_CollectSequencingArtifactMetrics.py
picard_tool/tools/picard_buildbamindex.py
picard_tool/tools/picard_calculatehsmetrics.py
picard_tool/tools/picard_calculatehsmetrics_gdc.py
picard_tool/tools/picard_calculatehsmetrics_target.py
picard_tool/tools/picard_calculatehsmetrics_tcga.py
picard_tool/tools/picard_collectoxogmetrics.py
picard_tool/tools/picard_collectsequencingartifactmetrics.py
picard_tool/tools/picard_collectwgsmetrics.py
picard_tool/tools/picard_markduplicates.py
picard_tool/tools/picard_mergesamfiles.py
picard_tool/tools/picard_sortsam.py
picard_tool/tools/picard_util.py
picard_tool/tools/picard_validatesamfile.py
picard_tool-0.106.dist-info/DESCRIPTION.rst
picard_tool-0.106.dist-info/METADATA
picard_tool-0.106.dist-info/RECORD
picard_tool-0.106.dist-info/WHEEL
picard_tool-0.106.dist-info/metadata.json
picard_tool-0.106.dist-info/top_level.txt
